{"$type":"System.Collections.Generic.List`1[[Products.Product, Products]], mscorlib","$values":[{"$type":"Products.Food, Products","ProductType":0,"Name":"Bread","PurchasePrice":2.0,"Number":2,"MarkUp":2.0,"UnitPrice":4.0,"AllPrice":8.0},{"$type":"Products.Clothes, Products","ProductType":1,"Name":"Trousers","PurchasePrice":2.0,"Number":15,"MarkUp":2.0,"UnitPrice":4.0,"AllPrice":60.0},{"$type":"Products.Food, Products","ProductType":0,"Name":"Juice","PurchasePrice":6.0,"Number":1,"MarkUp":2.0,"UnitPrice":8.0,"AllPrice":8.0},{"$type":"Products.Clothes, Products","ProductType":1,"Name":"Hat","PurchasePrice":2.0,"Number":5,"MarkUp":2.0,"UnitPrice":4.0,"AllPrice":20.0}]}
